{
  "category": "military",
  "last_updated": "2026-07-19T22:37:13.921381+00:00",
  "items": [
    {
      "title": "Can new drones, 3D printers defeat distance\u2019s tyranny? RIMPAC aims to find out",
      "url": "https://www.defenseone.com/technology/2026/07/can-new-drones-3d-printers-defeat-distances-tyranny-rimpac-aims-find-out/414825/",
      "source": "Defense One - Tech",
      "published": "2026-07-16T20:36:41+00:00"
    },
    {
      "title": "How a former Marine is rewriting the future of battlefield AI",
      "url": "https://www.defenseone.com/technology/2026/07/how-former-marine-rewriting-future-battlefield-ai/414758/",
      "source": "Defense One - Tech",
      "published": "2026-07-14T20:11:28+00:00"
    },
    {
      "title": "AI can now power every stage of a cyberattack",
      "url": "https://www.defenseone.com/technology/2026/07/ai-once-relegated-helping-hackers-certain-tasks-can-now-power-every-stage-cyberattack/414749/",
      "source": "Defense One - Tech",
      "published": "2026-07-14T01:00:00+00:00"
    },
    {
      "title": "How Ukraine won the first great robot war",
      "url": "https://www.defenseone.com/technology/2026/07/how-ukraine-won-first-great-robot-war/414658/",
      "source": "Defense One - Tech",
      "published": "2026-07-08T21:02:31+00:00"
    },
    {
      "title": "Lightweight cells powered by nuclear waste could drive tomorrow's drones",
      "url": "https://www.defenseone.com/technology/2026/07/these-light-weight-power-cells-run-nuclear-waste-and-could-power-next-gen-drones/414585/",
      "source": "Defense One - Tech",
      "published": "2026-07-03T12:00:00+00:00"
    },
    {
      "title": "GenAI.mil records almost 1.7M users, plans new model additions",
      "url": "https://www.defenseone.com/technology/2026/07/genaimil-records-almost-17m-users-plans-new-model-additions/414569/",
      "source": "Defense One - Tech",
      "published": "2026-07-02T13:00:00+00:00"
    },
    {
      "title": "Pentagon recruiting new tech talent for AI implementation",
      "url": "https://www.defenseone.com/technology/2026/06/pentagon-recruiting-new-tech-talent-ai-implementation/414528/",
      "source": "Defense One - Tech",
      "published": "2026-06-30T14:04:38+00:00"
    },
    {
      "title": "Pentagon launches \u2018War Force\u2019 initiative to onboard tech talent",
      "url": "https://www.defenseone.com/technology/2026/06/pentagon-launches-war-force-initiative-onboard-tech-talent/414523/",
      "source": "Defense One - Tech",
      "published": "2026-06-30T13:45:00+00:00"
    },
    {
      "title": "Army using AI, robot boats for Pacific logistics",
      "url": "https://www.defenseone.com/technology/2026/06/army-using-ai-robot-boats-pacific-logistics/414525/",
      "source": "Defense One - Tech",
      "published": "2026-06-30T11:22:25+00:00"
    },
    {
      "title": "Agentic-AI tools aim to give US commanders new target options \u2018within seconds\u2019",
      "url": "https://www.defenseone.com/technology/2026/06/agentic-ai-tool-aims-give-us-commanders-new-target-options-within-seconds/414491/",
      "source": "Defense One - Tech",
      "published": "2026-06-28T12:00:00+00:00"
    },
    {
      "title": "Could the Army\u2019s light squad vehicle power battlefield drones?",
      "url": "https://www.defenseone.com/technology/2026/06/could-armys-light-squad-vehicle-power-battlefield-drones/414485/",
      "source": "Defense One - Tech",
      "published": "2026-06-26T20:59:14+00:00"
    },
    {
      "title": "RIMPAC kicks off in Hawaii with a focus on experimentation",
      "url": "https://www.defenseone.com/technology/2026/06/rimpac-kicks-hawaii-focus-experimentation/414415/",
      "source": "Defense One - Tech",
      "published": "2026-06-25T08:07:20+00:00"
    },
    {
      "title": "Executive orders seek to hasten quantum computing\u2014and guard against its use",
      "url": "https://www.defenseone.com/technology/2026/06/orders-quantum-computers/414332/",
      "source": "Defense One - Tech",
      "published": "2026-06-22T22:06:00+00:00"
    },
    {
      "title": "CISA now has full Mythos Preview access, people familiar say",
      "url": "https://www.defenseone.com/technology/2026/06/cisa-mythos-preview-access/414276/",
      "source": "Defense One - Tech",
      "published": "2026-06-17T21:21:00+00:00"
    },
    {
      "title": "AI is taking some parts of background checks from 'months to hours,' clearance agency says",
      "url": "https://www.defenseone.com/technology/2026/06/background-checks-clearance/414225/",
      "source": "Defense One - Tech",
      "published": "2026-06-16T17:56:00+00:00"
    },
    {
      "title": "Shaped charges from coffee grounds? Pentagon science chief describes future of war",
      "url": "https://www.defenseone.com/technology/2026/06/pentagon-science-chief-future-war/414214/",
      "source": "Defense One - Tech",
      "published": "2026-06-16T15:21:19+00:00"
    },
    {
      "title": "Desert e-bike race \u2018the perfect\u2019 place to test military-vehicle AI",
      "url": "https://www.defenseone.com/technology/2026/06/desert-e-bike-race-perfect-place-test-military-vehicle-ai/413903/",
      "source": "Defense One - Tech",
      "published": "2026-06-02T05:29:59+00:00"
    },
    {
      "title": "Thanks largely to robots, Ukraine is now talking about winning, not just surviving",
      "url": "https://www.defenseone.com/technology/2026/06/ukraine-robots-winning/413902/",
      "source": "Defense One - Tech",
      "published": "2026-06-02T04:20:56+00:00"
    }
  ]
}